Workbook

Sheet Read me
A1: Microsoft Intune for Government - Discovery Pack
A2: Information gathering for the High Level Design. No design decisions, no solution content.
A4: Item | B4: Detail
A5: Purpose | B5: Gather every input needed to write the High Level Design. This pack is for information gathering only - it contains no design decisions and no solution content.
A6: How it is structured | B6: 'Discovery register' is the master list of questions. The other tabs are inventory templates and trackers that the register points to. 'Dashboard' counts progress. 'Sources' records every reference used and how current it is.
A7: How to use it | B7: Work the register domain by domain. For each row: agree who owns the answer, gather it by the method in 'How to obtain', record the answer and a link to the evidence, then set Status. Anything still Open when discovery closes becomes an assumption or an open issue in the HLD.
A8: Cells to fill in | B8: Shaded cells are for you to complete. Grey italic rows are worked examples showing the expected format - delete them before use.
A9: Traceability | B9: Every register row names the HLD section it feeds, so you can see what is still missing before writing starts, and nothing is gathered that no section needs.
A10: Government flags | B10: Rows shaded orange mark a capability that is absent or restricted in GCC High / DoD. Confirm each one against the Microsoft government service description before the design assumes it.
A11: Audit periods | B11: Some answers need observation, not a workshop. Start the elevation audit and any application usage telemetry in week one, or they become the critical path.
A12: Currency warning | B12: Intune changes monthly. Re-check the 'Sources' tab dates before relying on any feature statement; the government feature tables in particular move.
A13: Dashboard note | B13: The dashboard counts are formulas. They populate when the workbook is opened in a spreadsheet application.
A14: Built | B14: Built 2026-09-30, rebuilt through the discovery-creator skill 2026-09-30. Structure follows the Microsoft Intune planning guide (7 steps) and the Microsoft 'IDPDIG - Table templates' download; see 'Sources'.
A15: Refreshing this pack | B15: The spec beside this file is the source of truth. Update the pack with: /discovery-creator Microsoft Intune government --refresh microsoft-intune-government-discovery-pack.xlsx
A16: Next step | B16: When every Must-priority row is answered or owned: /hld-creator Microsoft Intune government --skeleton, then the full run.
A18: Tabs
A19: Discovery register | B19: Master question list: 169 questions across 17 domains, each traced to an HLD section.
A20: Device estate | B20: Per-cohort device inventory: counts, OS, join state, enrolment, Windows 11 readiness.
A21: Applications | B21: Application inventory and rationalisation decisions.
A22: GPO mapping | B22: GPO inventory and translation tracker for Group Policy analytics output.
A23: ConfigMgr | B23: Configuration Manager estate and co-management workload assessment.
A24: Identity and groups | B24: Tenants, directory sync, Conditional Access, group and RBAC structure.
A25: Network and PKI | B25: Sites, proxy and TLS inspection, endpoint allow-listing, certificate infrastructure.
A26: Security baselines | B26: Current and target baselines mapped to CIS, STIG, NCSC and Essential Eight.
A27: Government | B27: Environment, classification, accreditation route and the GCC High / DoD feature gap check.
A28: Personas | B28: Persona catalogue with apps, data classification and device needs.
A29: Licensing | B29: Entitlements held against entitlements each capability requires.
A30: Rollout rings | B30: Ring and pilot structure, and the deployment-plan constraints in public preview.
... A35: Dashboard | B35: Progress by domain and by status.

Sheet Discovery register
A1: Discovery register
A2: One row per question. Fill Answer, Evidence link, Status and Confidence. Orange rows flag a GCC High / DoD limitation to confirm.
A4: ID | B4: Domain | C4: Question or data point | D4: Why it matters (HLD section) | E4: How to obtain | F4: Who owns the answer | G4: Priority | H4: Workshop | I4: Government flag to confirm | J4: Answer | K4: Evidence link | L4: Status | M4: Confidence
A5: A01 | B5: Objectives and scope | C5: What business outcomes must endpoint management deliver over the next 12-36 months? | D5: 2, 3 Executive summary, scope | E5: Executive interview; existing strategy papers | F5: SRO / service owner | G5: Must | H5: W1 | L5: Open
A6: A02 | B6: Objectives and scope | C6: Which of the four Microsoft objectives apply: access to organisation apps and email; secure access on all devices; distribute IT; keep organisation data inside the organisation? | D6: 3, 4 Requirements | E6: Workshop against Microsoft planning guide Step 1 | F6: Service owner | G6: Must | H6: W1 | L6: Open
A7: A03 | B7: Objectives and scope | C7: Target operating model: cloud-native, co-managed, or hybrid with retained on-premises dependencies? | D7: 6, 16 ADR-002 | E7: Workshop; confirm against current estate findings | F7: Enterprise architect | G7: Must | H7: W1 | L7: Open
A8: A04 | B8: Objectives and scope | C8: Which agencies, departments or arm's-length bodies are in scope, and who owns each? | D8: 3 Scope | E8: Org chart; service catalogue | F8: Service owner | G8: Must | H8: W1 | L8: Open
A9: A05 | B9: Objectives and scope | C9: Is there an approved mandate and funding line, and for which financial years? | D9: 18, 19 | E9: Business case; finance | F9: Finance business partner | G9: Must | H9: W1 | L9: Open
A10: A06 | B10: Objectives and scope | C10: What is explicitly out of scope: classified or air-gapped estates, OT, servers, specialist devices? | D10: 3 Scope | E10: Workshop; confirm with security | F10: Security architect | G10: Must | H10: W1 | L10: Open
A11: A07 | B11: Objectives and scope | C11: What are the immovable dates: OS end of support, licence or contract renewal, accreditation deadlines, machinery-of-government changes? | D11: 19 Roadmap | E11: Contract register; vendor lifecycle pages | F11: Commercial lead | G11: Must | H11: W1 | L11: Open
A12: A08 | B12: Objectives and scope | C12: What does success look like as SMART measures per rollout phase? | D12: 4, 13 SLIs and SLOs | E12: Workshop; Microsoft planning guide Step 5 | F12: Service owner | G12: Must | H12: W1 | L12: Open
A13: A09 | B13: Objectives and scope | C13: What has been attempted before, and why did it stall? | D13: 3, 17 Risks | E13: Interview; project archive | F13: IT leadership | G13: Should | H13: W1 | L13: Open
A14: A10 | B14: Objectives and scope | C14: Who approves the design: enterprise architect, security authoriser, DPO, CAB, SIRO or Authorising Official? | D14: 1 Document control | E14: Governance map | F14: Service owner | G14: Must | H14: W1 | L14: Open
A15: A11 | B15: Objectives and scope | C15: What appetite is there for disruption to users - can devices be reset and rebuilt, or must changes be in-place? | D15: 19 Transition | E15: Workshop | F15: Service owner | G15: Must | H15: W1 | L15: Open
A16: A12 | B16: Objectives and scope | C16: Is a tenant consolidation, split or machinery-of-government change expected in the design's life? | D16: 3, 17 | E16: IT leadership; programme office | F16: Enterprise architect | G16: Should | H16: W1 | L16: Open
... A19: B03 | B19: Organisation | C19: Support model: L1/L2/L3 split, hours of service, agency-local IT responsibilities | D19: 13 Operations | E19: Interview; existing OLAs | F19: Service desk manager | G19: Must | H19: W8 | L19: Open
A20: B04 | B20: Organisation | C20: ITSM toolset and the integration expected with endpoint management | D20: 8, 14 | E20: Interview; tool admin | F20: ITSM owner | G20: Must | H20: W8 | I20: GOV GAP: the ServiceNow connector is not available in GCC High or DoD - plan an alternative integration | L20: Open
A21: B05 | B21: Organisation | C21: Change process, CAB cadence, and which endpoint changes could become pre-approved standard changes | D21: 14 Change enablement | E21: Change policy document | F21: Change manager | G21: Should | H21: W8 | L21: Open
A22: B06 | B22: Organisation | C22: CMDB: which system holds device records, what fields, and how is it populated? | D22: 14 Service configuration management | E22: CMDB export | F22: CMDB owner | G22: Must | H22: W8 | L22: Open
A23: B07 | B23: Organisation | C23: Where do runbooks and known errors live today? | D23: 13 Knowledge management | E23: Knowledge base review | F23: Service desk manager | G23: Should | H23: W8 | L23: Open
A24: B08 | B24: Organisation | C24: Who holds Global Administrator, Intune Administrator and equivalent roles today? | D24: 10 Identity and access | E24: Entra role assignment export | F24: Identity lead | G24: Must | H24: W3 | L24: Open
A25: B09 | B25: Organisation | C25: Training and certification levels of the team, and the gap to cloud-native operations | D25: 19 Operational readiness | E25: Skills matrix | F25: Endpoint team lead | G25: Should | H25: W8 | L25: Open
A26: B10 | B26: Organisation | C26: RACI for the device lifecycle: procure, provision, support, patch, retire, dispose | D26: 13, 19 | E26: Workshop | F26: Service owner | G26: Must | H26: W8 | L26: Open
A27: C01 | B27: Device estate | C27: Total device count by platform, OS version and build | D27: 3, 7, 11 | E27: Entra device export; Endpoint analytics; ConfigMgr; Defender device inventory | F27: Endpoint team | G27: Must | H27: W2 | L27: Open
A28: C02 | B28: Device estate | C28: Devices on an unsupported OS version that must be upgraded or replaced | D28: 7, 19 | E28: Compare inventory to Intune supported platforms list | F28: Endpoint team | G28: Must | H28: W2 | L28: Open
A29: C03 | B29: Device estate | C29: Windows 11 hardware readiness: capable versus not capable, and the top blocking requirement | D29: 19 Roadmap | E29: Endpoint analytics Work from anywhere report (device must have sent an event in the last 29 days) | F29: Endpoint team | G29: Must | H29: W2 | L29: Open
A30: C04 | B30: Device estate | C30: Device age, refresh cycle and warranty expiry by cohort | D30: 18, 19 | E30: Asset register; procurement records | F30: Asset manager | G30: Must | H30: W2 | L30: Open
A31: C05 | B31: Device estate | C31: Join state split: Entra joined, Entra hybrid joined, Entra registered, workgroup | D31: 7, 16 ADR-002 | E31: Entra devices export; ConfigMgr report | F31: Identity lead | G31: Must | H31: W2 | L31: Open
A32: C06 | B32: Device estate | C32: Current enrolment or management method for each platform | D32: 7 Logical components | E32: MDM console exports | F32: Endpoint team | G32: Must | H32: W2 | L32: Open
... A39: C13 | B39: Device estate | C39: Devices in low-bandwidth, disconnected or air-gapped locations | D39: 11, 12 | E39: Network inventory; site survey | F39: Network lead | G39: Must | H39: W6 | L39: Open
A40: C14 | B40: Device estate | C40: Hardware vendors and models in use, and whether BIOS or firmware management is required | D40: 7, 11 | E40: Asset register | F40: Asset manager | G40: Should | H40: W2 | I40: GOV GAP: BIOS configuration profiles and DFCI management are not yet available in GCC High or DoD | L40: Open
A41: C15 | B41: Device estate | C41: Autopilot registration state and whether hardware hashes are held or obtainable from the vendor | D41: 7, 11 | E41: Intune Autopilot devices blade; vendor registration | F41: Endpoint team | G41: Must | H41: W2 | I41: GOV GAP: classic Windows Autopilot is not available in GCC High or DoD; Autopilot device preparation is partially available | L41: Open
A42: C16 | B42: Device estate | C42: Device naming convention and asset tagging standard | D42: 7, 14 | E42: Existing standard document | F42: Endpoint team | G42: Should | H42: W2 | L42: Open
A43: C17 | B43: Device estate | C43: Virtual desktop estate: AVD, Windows 365, VDI - in scope or not? | D43: 3, 11 | E43: Platform team | F43: Platform lead | G43: Should | H43: W2 | I43: GOV GAP: Windows Enterprise multi-session (AVD) is not available in GCC High or DoD | L43: Open
A44: C18 | B44: Device estate | C44: Device counts per agency and per site, to size rings and delegated scopes | D44: 11 Tenant topology | E44: Asset register aggregation | F44: Asset manager | G44: Must | H44: W2 | L44: Open
A45: D01 | B45: Personas | C45: Persona catalogue: office, frontline, field, executive, developer, privileged admin, contractor, counter staff | D45: 3, 4 | E45: Workshop with agency representatives | F45: Service owner | G45: Must | H45: W2 | L45: Open
A46: D02 | B46: Personas | C46: Per persona: applications required, offline working needs, peripherals, data classification handled | D46: 4, 7, 9 | E46: Workshop; app owner interviews | F46: Agency IT leads | G46: Must | H46: W2 | L46: Open
A47: D03 | B47: Personas | C47: Privileged users and whether privileged access workstations exist today | D47: 10 Security | E47: Security team interview | F47: Security architect | G47: Must | H47: W3 | L47: Open
A48: D04 | B48: Personas | C48: Users who need local admin or elevation, and what they actually elevate | D48: 10 Security | E48: Run an elevation policy in reporting-only mode for 2-4 weeks before deciding (MSEndpointMgr EPM guidance), then map to personas | F48: Security architect | G48: Must | H48: W3 | L48: Open
A49: D05 | B49: Personas | C49: Users needing accessibility adjustments or assisted digital support | D49: 4, 13 | E49: Accessibility lead; HR | F49: Accessibility lead | G49: Must | H49: W8 | L49: Open
A50: D06 | B50: Personas | C50: Contractors and third parties: who owns their devices and how do they get access? | D50: 3, 10 | E50: Contract register; identity team | F50: Security architect | G50: Must | H50: W3 | L50: Open
A51: D07 | B51: Personas | C51: Field and mobile workers with connectivity constraints | D51: 7, 11 | E51: Workshop | F51: Agency IT leads | G51: Should | H51: W2 | L51: Open
A52: D08 | B52: Personas | C52: How executives and VIPs will be handled in rollout - Microsoft advises pilots should not be executives | D52: 19 Transition | E52: Workshop | F52: Service owner | G52: Should | H52: W9 | L52: Open
A53: E01 | B53: Licensing and cost | C53: Current licence SKUs and counts: M365 E3/E5/G3/G5, EMS, Intune Plan 1 / Plan 2 / Suite | D53: 18 Cost | E53: M365 admin centre licence report | F53: Licensing manager | G53: Must | H53: W1 | L53: Open
A54: E02 | B54: Licensing and cost | C54: Is Microsoft Entra ID P1 or P2 held? It underpins Autopilot, Conditional Access and dynamic groups | D54: 7, 10, 18 | E54: Licence report | F54: Licensing manager | G54: Must | H54: W1 | L54: Open
A55: E03 | B55: Licensing and cost | C55: Defender for Endpoint entitlement and plan | D55: 10 Security | E55: Licence report | F55: Licensing manager | G55: Must | H55: W3 | L55: Open
A56: E04 | B56: Licensing and cost | C56: Which Intune Suite capabilities are entitled or required: EPM, Remote Help, Advanced Analytics, Cloud PKI, Tunnel, specialty devices? | D56: 7, 18 | E56: Licence report; verify current packaging with Microsoft | F56: Licensing manager | G56: Must | H56: W1 | I56: GOV GAP: Cloud PKI and Remote Help are GCC High only and not supported in DoD | L56: Open
A57: E05 | B57: Licensing and cost | C57: Per-user versus per-device licensing needs for shared and kiosk devices | D57: 18 Cost | E57: Licence report; device cohort data | F57: Licensing manager | G57: Must | H57: W1 | L57: Open
A58: E06 | B58: Licensing and cost | C58: Incumbent MDM/EMM contract: cost, term, notice period and exit obligations | D58: 14, 18 | E58: Contract register | F58: Commercial lead | G58: Must | H58: W1 | L58: Open
A59: E07 | B59: Licensing and cost | C59: Configuration Manager licensing and co-management entitlement | D59: 18 | E59: Licence report | F59: Licensing manager | G59: Should | H59: W5 | L59: Open
A60: E08 | B60: Licensing and cost | C60: Budget envelope by financial year, and what it must cover | D60: 18 Cost | E60: Finance | F60: Finance business partner | G60: Must | H60: W1 | L60: Open
A61: E09 | B61: Licensing and cost | C61: Chargeback or recharge model across agencies | D61: 18 FinOps | E61: Finance | F61: Finance business partner | G61: Should | H61: W1 | L61: Open
A62: E10 | B62: Licensing and cost | C62: Current cost of build, imaging and support per device, as the baseline to improve on | D62: 18 Cost | E62: Finance; service desk metrics | F62: Finance business partner | G62: Should | H62: W8 | L62: Open
A63: F01 | B63: Identity and access | C63: How many Entra tenants exist, and in which cloud: commercial, GCC, GCC High, DoD or a national sovereign cloud? | D63: 11 ADR-001 | E63: Entra portal; licensing records | F63: Identity lead | G63: Must | H63: W3 | I63: GOV GAP: there is no built-in migration between the commercial service and the government cloud - devices must unenrol and re-enrol | L63: Open
A64: F02 | B64: Identity and access | C64: Directory synchronisation topology: Entra Connect or cloud sync, OU scope, filtering rules | D64: 8 Integration | E64: Entra Connect configuration export | F64: Identity lead | G64: Must | H64: W3 | L64: Open
A65: F03 | B65: Identity and access | C65: Authentication methods in use, MFA coverage, and the target for phishing-resistant authentication | D65: 10 Security | E65: Entra authentication methods report | F65: Identity lead | G65: Must | H65: W3 | L65: Open
A66: F04 | B66: Identity and access | C66: Existing Conditional Access policies, their exclusions, and break-glass account arrangements | D66: 10 Security | E66: Conditional Access export (Graph or portal) | F66: Identity lead | G66: Must | H66: W3 | L66: Open
A67: F05 | B67: Identity and access | C67: Group strategy: security groups, dynamic membership rules, naming standard and ownership | D67: 7, 8 | E67: Entra groups export; Microsoft planning guide Step 4 group review | F67: Identity lead | G67: Must | H67: W3 | L67: Open
A68: F06 | B68: Identity and access | C68: Distribution lists that must become Entra groups to be usable for targeting | D68: 8 | E68: Exchange DL export | F68: Identity lead | G68: Should | H68: W3 | L68: Open
A69: F07 | B69: Identity and access | C69: Delegated administration model: scope tags, role assignments and agency separation | D69: 10, 11 ADR-003 | E69: Intune RBAC export | F69: Identity lead | G69: Must | H69: W3 | L69: Open
A70: F08 | B70: Identity and access | C70: Federation to national or cross-government identity services | D70: 8 Integration | E70: Identity team | F70: Identity lead | G70: Should | H70: W3 | L70: Open
A71: F09 | B71: Identity and access | C71: Guest and B2B access to resources that managed devices reach | D71: 10 | E71: Entra external identities settings | F71: Identity lead | G71: Should | H71: W3 | L71: Open
A72: F10 | B72: Identity and access | C72: Is Privileged Identity Management in use for administrative roles? | D72: 10 Security | E72: Entra PIM configuration | F72: Identity lead | G72: Must | H72: W3 | L72: Open
A73: F11 | B73: Identity and access | C73: Is device compliance already used as a Conditional Access condition? | D73: 10 Security | E73: Conditional Access export | F73: Identity lead | G73: Must | H73: W3 | L73: Open
A74: F12 | B74: Identity and access | C74: How are licences assigned - group-based or direct - and who governs that? | D74: 8, 18 | E74: Entra licence assignment report | F74: Licensing manager | G74: Should | H74: W3 | L74: Open
A75: G01 | B75: Existing policy | C75: Full export of every Group Policy Object and the OUs each is linked to | D75: 7 Logical components | E75: Get-GPOReport -All -ReportType Xml; GPMC review | F75: AD administrator | G75: Must | H75: W5 | L75: Open
... A83: G09 | B83: Existing policy | C83: Imaging and OS deployment process today, including task sequences and drivers | D83: 19 Transition | E83: ConfigMgr console; build documentation | F83: Endpoint team | G83: Must | H83: W5 | L83: Open
A84: G10 | B84: Existing policy | C84: Scripts and remediations relied on for endpoint health | D84: 13 Operations | E84: Script repository; ConfigMgr configuration items | F84: Endpoint team | G84: Should | H84: W5 | I84: GOV GAP: Remediations are not available in GCC High or DoD | L84: Open
A85: G11 | B85: Existing policy | C85: Certificate profiles in use and the infrastructure behind them (NDES, SCEP, PKCS) | D85: 7, 8 | E85: PKI documentation; MDM console | F85: PKI owner | G85: Must | H85: W6 | L85: Open
A86: G12 | B86: Existing policy | C86: If an Intune tenant already exists, a full export of its current configuration | D86: 7 | E86: IntuneCD, IntuneManagement or a Graph export - see Tooling tab | F86: Endpoint team | G86: Must | H86: W5 | L86: Open
A87: H01 | B87: Applications | C87: Complete application inventory with deployment counts and last-used data | D87: 7 Logical components | E87: ConfigMgr SQL views and SSRS reports (System Center Dudes method); Intune app reports | F87: Application owner | G87: Must | H87: W4 | L87: Open
A88: H02 | B88: Applications | C88: Business owner, criticality and user count for each application | D88: 4, 7 | E88: Application owner interviews | F88: Application owner | G88: Must | H88: W4 | L88: Open
A89: H03 | B89: Applications | C89: Packaging format of each application: MSI, EXE, MSIX, Store, Win32, LOB | D89: 7 | E89: Inventory analysis | F89: Packaging team | G89: Must | H89: W4 | L89: Open
A90: H04 | B90: Applications | C90: Applications with dependencies, supersedence chains, or that only install inside a task sequence | D90: 7, 19 | E90: ConfigMgr dependency report | F90: Packaging team | G90: Must | H90: W4 | L90: Open
A91: H05 | B91: Applications | C91: Applications that require administrative rights at run time | D91: 10 | E91: Packaging review; elevation audit data | F91: Packaging team | G91: Must | H91: W4 | L91: Open
A92: H06 | B92: Applications | C92: Licence-restricted applications and their activation or entitlement method | D92: 18 | E92: Licence register | F92: Licensing manager | G92: Should | H92: W4 | L92: Open
A93: H07 | B93: Applications | C93: Mobile application estate: Apple VPP tokens, managed Google Play, line-of-business apps and their source files | D93: 7, 8 | E93: MDM console; ABM and Play console | F93: Endpoint team | G93: Must | H93: W4 | L93: Open
A94: H08 | B94: Applications | C94: Applications that only need protecting on unmanaged devices, rather than deploying | D94: 7 ADR-004 | E94: Workshop with app owners | F94: Security architect | G94: Should | H94: W4 | L94: Open
A95: H09 | B95: Applications | C95: Web applications and browser dependencies, including any legacy compatibility mode needs | D95: 7, 8 | E95: Browser inventory; app owner interviews | F95: Application owner | G95: Must | H95: W4 | L95: Open
A96: H10 | B96: Applications | C96: Rationalisation candidates: applications with no installs or launches in 90 days | D96: 7, 18 | E96: Inventory analysis | F96: Application owner | G96: Should | H96: W4 | L96: Open
... A103: I05 | B103: Updates | C103: Patch timelines mandated by the applicable framework (Essential Eight, CAF, STIG, agency policy) | D103: 15 Compliance | E103: Security policy; regulator guidance | F103: Security architect | G103: Must | H103: W7 | L103: Open
A104: I06 | B104: Updates | C104: Confirm which update capabilities exist in the target cloud before designing the update approach | D104: 11, 15 | E104: Microsoft Intune government service description | F104: Endpoint team | G104: Must | H104: W7 | I104: GOV GAP: Windows Autopatch and the feature, quality, expedite and driver update policies are not available in GCC High or DoD (planned) | L104: Open
A105: I07 | B105: Updates | C105: Maintenance windows, change freezes and peak periods that constrain updates | D105: 14 | E105: Change calendar | F105: Change manager | G105: Must | H105: W8 | L105: Open
A106: I08 | B106: Updates | C106: Content delivery and bandwidth optimisation used today | D106: 11 | E106: Network team; ConfigMgr DP report | F106: Network lead | G106: Should | H106: W6 | I106: GOV GAP: Microsoft Connected Cache for Enterprise and Delivery Optimization for Win32 apps are not available in GCC High or DoD | L106: Open
A107: J01 | B107: Security | C107: Endpoint detection and response tool in place, its coverage and onboarding method | D107: 10 Security | E107: Defender or third-party console export | F107: Security operations | G107: Must | H107: W3 | L107: Open
A108: J02 | B108: Security | C108: Disk encryption state by platform and where recovery keys are escrowed today | D108: 9, 10 | E108: Current encryption reporting | F108: Security architect | G108: Must | H108: W3 | L108: Open
A109: J03 | B109: Security | C109: How many users hold local administrator rights, and what do they actually use them for? | D109: 10 | E109: Elevation audit in reporting-only mode for 2-4 weeks; AD local admin group audit | F109: Security architect | G109: Must | H109: W3 | L109: Open
A110: J04 | B110: Security | C110: Is a local administrator password solution in use, and where are passwords escrowed? | D110: 10 | E110: Current LAPS configuration | F110: Security architect | G110: Must | H110: W3 | L110: Open
A111: J05 | B111: Security | C111: Anti-malware, attack surface reduction and exploit protection posture today | D111: 10 | E111: Defender configuration export | F111: Security operations | G111: Must | H111: W3 | L111: Open
A112: J06 | B112: Security | C112: Mobile threat defence product in use, and whether it supports the target government cloud | D112: 10 | E112: Vendor confirmation; Intune connector list in the target tenant | F112: Security architect | G112: Must | H112: W7 | L112: Open
A113: J07 | B113: Security | C113: SIEM platform, required log sources and retention period for endpoint logs | D113: 10, 13 | E113: Security operations | F113: Security operations | G113: Must | H113: W3 | L113: Open
A114: J08 | B114: Security | C114: Which configuration baseline must the design meet: CIS level, DISA STIG, NCSC device guidance, Essential Eight? | D114: 10, 15 | E114: Security policy; accreditation requirements | F114: Security architect | G114: Must | H114: W7 | L114: Open
A115: J09 | B115: Security | C115: Cryptographic requirements, including any need for FIPS 140-3 validated modules | D115: 10 | E115: Security policy | F115: Security architect | G115: Must | H115: W7 | L115: Open
A116: J10 | B116: Security | C116: Vulnerability management tooling, scan coverage and remediation SLAs for endpoints | D116: 10 | E116: Vulnerability management team | F116: Security operations | G116: Must | H116: W3 | L116: Open
A117: J11 | B117: Security | C117: Incident response process for endpoints and the regulatory reporting clock that applies | D117: 14, 15 | E117: IR plan; regulator guidance | F117: Security operations | G117: Must | H117: W7 | L117: Open
A118: J12 | B118: Security | C118: Zero trust target maturity and the model being measured against | D118: 10 | E118: Security strategy; CISA Zero Trust Maturity Model or equivalent | F118: Security architect | G118: Must | H118: W7 | L118: Open
... A132: L04 | B132: Government | C132: Accreditation route and the evidence pack required: ATO, FedRAMP, IRAP, GovAssure or equivalent | D132: 15 | E132: Assurance team | F132: Information assurance lead | G132: Must | H132: W7 | L132: Open
A133: L05 | B133: Government | C133: Check every required capability against the government feature tables before the design assumes it | D133: 7, 11, 15 | E133: Microsoft Intune government service overview - supported, planned, and not-available tables | F133: Endpoint architect | G133: Must | H133: W7 | I133: GOV GAP: run this check explicitly - the not-available list includes Autopilot, Remediations, the ServiceNow connector, Store for Business, the Power BI connector for the data warehouse, Windows Backup for Organizations and AVD multi-session | L133: Open
A134: L06 | B134: Government | C134: Is tenant hardening against a published STIG required, and which one? | D134: 10, 15 | E134: public.cyber.mil STIG document library (MDM/EMM); security policy | F134: Security architect | G134: Must | H134: W7 | L134: Open
A135: L07 | B135: Government | C135: Do CJIS, IRS 1075 or a specific DoD impact level apply to any data on these devices? | D135: 15 | E135: Information asset register; legal | F135: Information assurance lead | G135: Must | H135: W7 | L135: Open
...

Sheet Device estate
A1: Device estate inventory
A2: One row per device cohort (platform + ownership + agency). Aggregate from Entra, Endpoint analytics, Configuration Manager and Defender. Grey row is an example.
A4: Cohort ID | B4: Agency / business unit | C4: Platform | D4: OS version or build | E4: Ownership | F4: Count | G4: Join state | H4: Current management | I4: Enrolment method today | J4: Windows 11 capable | K4: Top readiness blocker | L4: Refresh due | M4: Data classification | N4: Notes | O4: Source of data | P4: Date captured
A5: EX-01 | B5: Example: Revenue directorate | C5: Windows | D5: Windows 10 22H2 | E5: Corporate | F5: 1240 | G5: Entra hybrid joined | H5: Configuration Manager | I5: GPO + ConfigMgr client | J5: Not capable | K5: TPM 2.0 absent | L5: 2027 Q2 | M5: OFFICIAL | N5: Delete this example row before use | O5: Endpoint analytics export | P5: 2026-09-30

Sheet Applications
A1: Application inventory and rationalisation
A2: One row per application. Source counts from Configuration Manager reporting and the current MDM. Decide keep / replace / retire during discovery, not during design.
A4: App ID | B4: Application | C4: Vendor | D4: Version | E4: Business owner | F4: Criticality | G4: Users | H4: Install count | I4: Packaging format | J4: Dependencies | K4: Needs admin rights | L4: In task sequence | M4: Platform | N4: Keep / replace / retire | O4: Repackaging effort | P4: Notes
A5: EX-01 | B5: Example: Case management client | C5: Contoso | D5: 7.2.1 | E5: Revenue directorate | F5: Critical | G5: 900 | H5: 1120 | I5: MSI + transform | J5: SQL native client | K5: Yes - at run time | L5: Yes | M5: Windows | N5: Keep | O5: High | P5: Delete this example row before use

Sheet GPO mapping
A1: Group Policy inventory and translation tracker
A2: Populate from Get-GPOReport -All -ReportType Xml, then from the Group Policy analytics report. Expect the difficult 20 percent to consume most of the effort.
A4: GPO ID | B4: GPO name | C4: Linked OU(s) | D4: Purpose | E4: Owner | F4: Last modified | G4: Setting count | H4: Supported in MDM | I4: Unsupported settings | J4: Target Intune mechanism | K4: Translation difficulty | L4: Decision | M4: Notes
A5: EX-01 | B5: Example: Corp - Workstation security | C5: OU=Workstations | D5: Baseline lockdown | E5: Unowned | F5: 2014-06-11 | G5: 214 | H5: 182 of 214 | I5: Drive maps, logon script | J5: Settings catalogue | K5: Medium | L5: Replace | M5: Unowned GPO - deprecation candidate; delete this example row

Sheet ConfigMgr
A1: Configuration Manager estate and co-management assessment
A2: Capture the current hierarchy and, for each co-management workload, where it is authoritative today and where it should end up.
A4: Item | B4: Current state | C4: Evidence | D4: Target state | E4: Decision needed | F4: Owner | G4: Notes
A5: Example: Compliance policies workload | B5: Configuration Manager | C5: Co-management dashboard | D5: Intune | E5: Switch sequence and pilot collection | F5: ConfigMgr administrator | G5: Delete this example row before use

Sheet Identity and groups
A1: Identity, groups and delegated administration
A2: Tenants, synchronisation, Conditional Access and the group and RBAC structure that targeting will depend on.
A4: Item | B4: Current state | C4: Evidence | D4: Constraint or requirement | E4: Owner | F4: Notes
A5: Example: Conditional Access policy set | B5: 14 policies, 3 with broad exclusions | C5: Graph export 2026-09-30 | D5: Exclusions must be justified and time-bound | E5: Identity lead | F5: Delete this example row before use

Sheet Network and PKI
A1: Network, connectivity and certificate infrastructure
A2: One row per site or network zone, plus the PKI components. Confirm the endpoint list that applies to the target cloud before allow-listing.
A4: Site or component | B4: Type | C4: Users or devices | D4: Bandwidth | E4: Proxy in path | F4: TLS inspection | G4: Required endpoints allow-listed | H4: Certificate dependency | I4: Owner | J4: Notes
A5: Example: Regional office - Leeds | B5: Branch site | C5: 420 | D5: 200 Mbps | E5: Yes | F5: Yes - exemption needed | G5: Not yet | H5: Wi-Fi certificate via SCEP | I5: Network lead | J5: Delete this example row before use

Sheet Security baselines
A1: Security baseline and control mapping
A2: What is enforced today, what the accreditation requires, and the gap between them. Complete before section 10 of the HLD is drafted.
A4: Control area | B4: Enforced today | C4: How | D4: Required baseline | E4: Framework reference | F4: Gap | G4: Evidence needed for accreditation | H4: Owner
A5: Example: Disk encryption | B5: Yes - on laptops only | C5: GPO + MBAM | D5: All platforms, keys escrowed in cloud | E5: CIS Control 3; NCSC device guidance | F5: Desktops and macOS not covered | G5: Encryption compliance report | H5: Security architect

Sheet Government
A1: Government environment, assurance and feature-gap check
A2: Work through every capability the design may rely on and confirm its availability in the target cloud. Source: Microsoft Intune government service overview (see Sources).
A4: Capability or obligation | B4: Needed? | C4: Availability in target cloud | D4: Source checked | E4: Date checked | F4: Impact if unavailable | G4: Mitigation or alternative | H4: Owner | I4: Status
A5: Windows Autopilot (classic) | C5: Not available in GCC High / DoD | D5: Intune government service overview | E5: 2026-09-30 | F5: No zero-touch provisioning by that route | G5: Assess Autopilot device preparation coverage | H5: Endpoint architect | I5: Open
A6: Windows Autopatch and update policies | C6: Planned, not yet available in GCC High / DoD | D6: Intune government service overview | E6: 2026-09-30 | F6: Update rings must be designed another way | G6: Design against available update controls | H6: Endpoint architect | I6: Open
A7: Remediations (proactive scripts) | C7: Not available in GCC High / DoD | D7: Intune government service overview | E7: 2026-09-30 | F7: No scripted self-healing | G7: Alternative tooling or accept | H7: Endpoint architect | I7: Open
A8: ServiceNow connector | C8: Not available in GCC High / DoD | D8: Intune government service overview | E8: 2026-09-30 | F8: No native ITSM device sync | G8: Graph-based integration | H8: ITSM owner | I8: Open
A9: Remote Help | C9: GCC High only; not supported in DoD | D9: Intune government service overview | E9: 2026-09-30 | F9: Remote assistance gap for DoD | G9: Alternative remote support tooling | H9: Service desk manager | I9: Open
A10: Cloud PKI | C10: GCC High only; not supported in DoD | D10: Intune government service overview | E10: 2026-09-30 | F10: Certificate issuance needs existing PKI | G10: SCEP or PKCS with connectors | H10: PKI owner | I10: Open
A11: BIOS / DFCI management | C11: Planned, not yet available in GCC High / DoD | D11: Intune government service overview | E11: 2026-09-30 | F11: No cloud firmware control | G11: Vendor tooling | H11: Endpoint architect | I11: Open
A12: Device Health Attestation | C12: Planned, not yet available in GCC High / DoD | D12: Intune government service overview | E12: 2026-09-30 | F12: Attestation-based compliance unavailable | G12: Alternative compliance signals | H12: Security architect | I12: Open
A13: AVD multi-session / Windows 365 | C13: Multi-session not available in GCC High / DoD | D13: Intune government service overview | E13: 2026-09-30 | F13: Virtual desktop scope affected | G13: Confirm scope | H13: Platform lead | I13: Open
A14: Power BI connector for the data warehouse | C14: Not available in GCC High / DoD | D14: Intune government service overview | E14: 2026-09-30 | F14: Custom reporting route needed | G14: Graph or Log Analytics export | H14: Reporting lead | I14: Open
A15: Commercial to government cloud migration | C15: No built-in migration in either direction | D15: Intune government service overview | E15: 2026-09-30 | F15: Every device must unenrol and re-enrol | G15: Plan re-enrolment as a project phase | H15: Service owner | I15: Open
A16: STIG hardening of the tenant | C16: STIG library published on public.cyber.mil | D16: Intune government service overview | E16: 2026-09-30 | F16: Accreditation finding | G16: Apply applicable MDM/EMM STIG | H16: Security architect | I16: Open

Sheet Personas
A1: Persona catalogue
A2: One row per persona. Personas drive configuration profiles, application sets and compliance policy, so complete this before design starts.
A4: Persona ID | B4: Persona | C4: Population | D4: Agencies | E4: Device type and ownership | F4: Key applications | G4: Data classification | H4: Connectivity | I4: Admin rights needed | J4: Accessibility needs | K4: Notes
A5: P-01 | B5: Example: Field inspector | C5: 620 | D5: Regulatory directorate | E5: Corporate Windows laptop + iOS phone | F5: Case management, Teams, camera capture | G5: OFFICIAL-SENSITIVE | H5: Mobile, often offline | I5: No | J5: Screen reader for 12 users | K5: Delete this example row before use

Sheet Licensing
A1: Licensing and entitlement check
A2: What is held, what each required capability needs, and the gap. Confirm current packaging with Microsoft - it changes.
A4: Capability | B4: Licence or SKU required | C4: Held today | D4: Count held | E4: Count needed | F4: Gap | G4: Annual cost impact | H4: Source checked | I4: Owner
A5: Example: Conditional Access | B5: Microsoft Entra ID P1 | C5: Yes | D5: 8400 | E5: 9200 | F5: 800 | G5: To be confirmed | H5: M365 admin centre licence report | I5: Licensing manager

Sheet Rollout rings
A1: Rollout rings and pilot design
A2: Ring structure, populations and dates. Note the constraints on the deployments feature in public preview before depending on it.
A4: Ring | B4: Purpose | C4: Population | D4: Agencies | E4: Device count | F4: Entry criteria | G4: Exit criteria | H4: Planned start | I4: Planned end | J4: Owner | K4: Notes
A5: Ring 0 | B5: Example: IT build and break | C5: Endpoint team | D5: Central IT | E5: 50 | F5: Test tenant validated complete | G5: No P1 incidents for 5 working days | H5: 2026-11-03 | I5: 2026-11-17 | J5: Endpoint team lead | K5: Microsoft advises pilots should not be executives; delete this example row

Sheet Tooling
A1: Data collection tooling
A2: How each part of the discovery is actually gathered. Check the caveat column before committing to a tool. Read-only permissions are sufficient for discovery.
A4: Tool | B4: Publisher | C4: Official or community | D4: What it gathers | E4: Access or permissions needed | F4: Output | G4: Caveats | H4: Reference
A5: Microsoft Intune admin centre reports | B5: Microsoft | C5: Official | D5: Device, compliance, app install and enrolment failure reporting | E5: Intune Reader role | F5: CSV export | G5: Only covers devices already enrolled | H5: https://learn.microsoft.com/intune/device-management/reports/overview
A6: Endpoint analytics - Work from anywhere | B6: Microsoft | C6: Official | D6: Windows 11 hardware readiness, cloud management and identity posture | E6: Intune Reader; devices must be enrolled or co-managed | F6: Portal and CSV | G6: A device only appears if it has sent an event in the last 29 days; readiness does not affect the score | H6: https://learn.microsoft.com/intune/analytics/work-from-anywhere
A7: Group Policy analytics | B7: Microsoft | C7: Official | D7: Which GPO settings translate to MDM, and which are deprecated or unsupported | E7: Intune administrator; GPO XML export | F7: Portal report; can generate a settings catalogue policy | G7: Analyses settings, not intent - an unowned GPO still needs a human decision | H7: https://learn.microsoft.com/intune/device-configuration/import-group-policy-analytics
A8: Get-GPOReport (Group Policy PowerShell) | B8: Microsoft | C8: Official | D8: Complete GPO export in XML or HTML | E8: Domain read access | F8: XML / HTML | G8: Produces volume, not priority - pair with an ownership register | H8: Built into RSAT
A9: Microsoft Graph PowerShell SDK | B9: Microsoft | C9: Official | D9: Anything in Intune and Entra: devices, policies, groups, assignments, Conditional Access | E9: Read-only Graph scopes such as DeviceManagementConfiguration.Read.All | F9: JSON / CSV | G9: Beta endpoints change without notice; pin what you rely on | H9: https://learn.microsoft.com/powershell/microsoftgraph/installation
A10: Configuration Manager reports and SQL views | B10: Microsoft | C10: Official | D10: Applications, packages, task sequences, collections, client health, deployment counts | E10: ConfigMgr read access; SQL read for direct queries | F10: SSRS / CSV | G10: Query views (v_Package, v_Advertisement, v_TaskSequencePackage), not tables | H10: https://www.systemcenterdudes.com/sccm-to-microsoft-intune-migration-identifying-applications-packages-and-task-sequences/
A11: Intune tenant documentation script | B11: Microsoft | C11: Official but archived | D11: Read-only Markdown inventory of around 30 configuration categories, plus reverse assignment reports | E11: Eight read-only Graph scopes; PowerShell 7+ | F11: Markdown | G11: Repository was archived on 22 September 2026 and is read-only - usable, but unmaintained | H11: https://github.com/microsoft/intune-tenant-doc
A12: IntuneCD | B12: Community (Tobias Almen) | C12: Community | D12: Backup, documentation and continuous delivery of Intune configuration | E12: Entra app registration with Graph permissions | F12: YAML / JSON plus Markdown as-built | G12: Third-party code - review before running against a government tenant | H12: https://stealthpuppy.com/automate-intune-documentation-github/
A13: IntuneManagement | B13: Community (Mikael Karlsson) | C13: Community | D13: Export, import, copy, compare and document 30+ object types across tenants | E13: Graph permissions via app registration | F13: JSON plus documentation output | G13: Cross-tenant import has known gaps - see the Microsoft export limitations table | H13: https://github.com/Micke-K/IntuneManagement
A14: Microsoft 365 admin centre setup guides | B14: Microsoft | C14: Official | D14: Environment-tailored setup and readiness guidance | E14: Global Reader at minimum | F14: Portal guidance | G14: Guidance, not an inventory | H14: https://learn.microsoft.com/microsoft-365/enterprise/setup-guides-for-microsoft-365
A15: IDPDIG table templates | B15: Microsoft | C15: Official | D15: Word table templates for planning, design, current-environment assessment, and test and validation | E15: None - public download | F15: DOCX | G15: Version 1.0, published 15 July 2024 - predates the 2026 government feature changes | H15: https://www.microsoft.com/download/details.aspx?id=103005
... A18: Elevation reporting in reporting-only mode | B18: Microsoft | C18: Official | D18: Which applications users actually elevate, by user and device, before rights are removed | E18: Intune administrator; EPM entitlement | F18: Portal dashboard | G18: Run for 2-4 weeks before deciding; needs the Intune Suite or EPM add-on | H18: https://msendpointmgr.com/2026/06/15/epm-part-1-the-end-of-local-admin-how-intune-endpoint-privilege-management-solves-a-problem-it-has-lived-with-for-decades/

Sheet Workshops
A1: Workshop and interview pack
A2: Nine sessions covering the register. Run W1 first; W7 needs the outputs of W2, W3 and W6.
A4: Ref | B4: Workshop | C4: Duration | D4: Attendees | E4: Inputs needed beforehand | F4: Outputs | G4: Register rows closed
A5: W1 | B5: Vision, scope and success measures | C5: 2 hours | D5: SRO, service owner, enterprise architect, finance, commercial | E5: Business case, existing strategy, contract register | F5: Agreed scope, objectives, SMART measures, decision makers | G5: A01-A12, E01-E10
A6: W2 | B6: Device estate and personas | C6: 3 hours | D6: Endpoint team, asset manager, agency IT leads | E6: Device exports, Endpoint analytics readiness data | F6: Cohort table, persona catalogue, shadow estate list | G6: C01-C18, D01-D08
A7: W3 | B7: Identity, access and security | C7: 3 hours | D7: Identity lead, security architect, security operations | E7: Entra exports, Conditional Access export, baseline documentation | F7: Identity model, control gap list, elevation audit plan | G7: F01-F12, J01-J12, B08
A8: W4 | B8: Applications | C8: 3 hours | D8: Application owners, packaging team, licensing manager | E8: Application inventory with install counts | F8: Rationalised application list with keep/replace/retire and effort bands | G8: H01-H12
A9: W5 | B9: Existing estate: Group Policy and Configuration Manager | C9: 3 hours | D9: AD administrator, ConfigMgr administrator, endpoint team | E9: GPO XML export, Group Policy analytics run, ConfigMgr reports | F9: GPO decision register, workload switch sequence | G9: G01-G12, I01-I04, Q01-Q08
A10: W6 | B10: Network, connectivity and PKI | C10: 2 hours | D10: Network lead, PKI owner, infrastructure lead | E10: Site list, proxy configuration, PKI documentation | F10: Endpoint allow-listing actions, certificate approach inputs | G10: K01-K10, C13, I08
A11: W7 | B11: Government environment, assurance and privacy | C11: 3 hours | D11: Information assurance lead, DPO, records manager, security architect, commercial | E11: Classification policy, accreditation requirements, outputs of W2, W3 and W6 | F11: Environment decision inputs, feature-gap register, evidence list | G11: L01-L14, M01-M06, J08-J12, O05
A12: W8 | B12: Operations, support and resilience | C12: 2 hours | D12: Service desk manager, endpoint team lead, change manager, CMDB owner | E12: 12 months of ticket data, BIA output | F12: Support model inputs, RTO/RPO, reporting needs | G12: B01-B10, N01-N06, O01-O04
A13: W9 | B13: Rollout, communications and training | C13: 2 hours | D13: Service owner, communications lead, agency business leads | E13: Cohort table, persona catalogue, business calendar | F13: Ring structure, phase dates, communications plan | G13: P01-P06, D08

Sheet RAID and decisions
A1: RAID log and decisions discovery must surface
A2: Anything the register cannot close becomes a row here, and then an assumption, open issue or ADR in the HLD.
A4: ID | B4: Type | C4: Description | D4: Impact if unresolved | E4: Owner | F4: Needed by | G4: HLD destination | H4: Status
A5: D-01 | B5: Decision | C5: Which cloud environment: commercial, GCC, GCC High, DoD or sovereign | D5: Blocks almost every other design decision, including feature availability | E5: SRO | F5: Before design starts | G5: Section 16 ADR-001 | H5: Open
A6: D-02 | B6: Decision | C6: Single shared tenant with delegated scopes, or a tenant per agency | D6: Determines RBAC, reporting and separation model | E6: Enterprise architect | F6: Before design starts | G6: Section 16 ADR-003 | H6: Open
A7: D-03 | B7: Decision | C7: Co-management retained, or cloud-only | D7: Determines migration scope and timeline | E7: Enterprise architect | F7: Before design starts | G7: Section 16 ADR-002 | H7: Open
A8: D-04 | B8: Decision | C8: Personally owned devices: application protection only, or full enrolment | D8: Changes scope, privacy position and support model | E8: SRO | F8: Before design starts | G8: Section 16 ADR-004 | H8: Open
A9: A-01 | B9: Assumption | C9: Jurisdiction is not yet confirmed; the skeleton covers US, UK, EU and Australia | D9: Section 15 cannot be written accurately, and the hosting decision stays open | E9: Information assurance lead | F9: Before design starts | G9: Section 17 assumptions | H9: Open
A10: R-01 | B10: Risk | C10: Government cloud feature gaps invalidate a design assumption late | D10: Rework and possible accreditation delay | E10: Endpoint architect | F10: During discovery | G10: Section 17 risks | H10: Open
A11: R-02 | B11: Risk | C11: Unowned Group Policy Objects carry unknown intent | D11: Settings lost or wrongly carried forward at migration | E11: AD administrator | F11: During discovery | G11: Section 17 risks | H11: Open

Sheet Sources
A1: Sources and currency assessment
A2: Every source used to build this pack, with its date and what was checked. Comment sections were reviewed for corrections where the platform exposes them.
A4: # | B4: Source | C4: Publisher | D4: Type | E4: Published or updated | F4: Accessed | G4: Used for | H4: Comment section assessment | I4: Currency warning
A5: 1 | B5: Planning guide to move to Microsoft Intune - https://learn.microsoft.com/intune/fundamentals/planning-guide | C5: Microsoft | D5: Official documentation | E5: Updated 2026-07-24 (ms.date 2026-05-28) | F5: 2026-09-30 | G5: The seven-step spine of this pack: objectives, device inventory, cost and licensing, existing policy review, rollout, communications, support | H5: Microsoft Learn has no reader comments; feedback goes to GitHub issues | I5: Re-check before each engagement
A6: 2 | B6: Migration guide to Microsoft Intune - https://learn.microsoft.com/intune/fundamentals/setup-migration | C6: Microsoft | D6: Official documentation | E6: Updated 2026-07-01 (ms.date 2025-12-15) | F6: 2026-09-30 | G6: Migration starting positions, co-management and tenant attach options, and the tenant-to-tenant export limitations table | H6: No comments on Microsoft Learn | I6: Export limitations table is the part most often out of date
A7: 3 | B7: Microsoft Intune Government Service overview - https://learn.microsoft.com/intune/fundamentals/government-service | C7: Microsoft | D7: Official documentation | E7: Updated 2026-09-25 (ms.date 2026-09-08) | F7: 2026-09-30 | G7: Every government feature gap on the Government tab, IL4/IL5 positioning, STIG library pointer, and the absence of a commercial-to-government migration path | H7: No comments on Microsoft Learn | I7: This is the fastest-moving source in the pack - features move between the supported, planned and unavailable tables
A8: 4 | B8: Deployment plans and deployments overview - https://learn.microsoft.com/intune/device-management/deployments/overview | C8: Microsoft | D8: Official documentation | E8: Updated 2026-09-21 (ms.date 2026-08-26) | F8: 2026-09-30 | G8: Ring-based rollout constraints recorded on the Rollout rings tab | H8: No comments on Microsoft Learn | I8: Public preview - Windows only, Required install intent only, minimum one hour between rings
A9: 5 | B9: Network endpoints for US government deployments - https://learn.microsoft.com/intune/intune-service/fundamentals/intune-us-government-endpoints | C9: Microsoft | D9: Official documentation | E9: Checked 2026-09-30 | F9: 2026-09-30 | G9: Confirms government tenants use *.manage.microsoft.us and login.microsoftonline.us rather than the commercial endpoints | H9: No comments on Microsoft Learn | I9: Endpoint lists change; re-check before firewall change requests
A10: 6 | B10: Work From Anywhere report in Endpoint analytics - https://learn.microsoft.com/intune/analytics/work-from-anywhere | C10: Microsoft | D10: Official documentation | E10: Checked 2026-09-30 | F10: 2026-09-30 | G10: Windows 11 hardware readiness discovery method and its 29-day activity window | H10: No comments on Microsoft Learn | I10: Direct fetch of this page failed once during research; content confirmed via Microsoft Learn search results - re-verify the URL
A11: 7 | B11: IDPDIG - Table templates (download id=103005) - https://www.microsoft.com/download/details.aspx?id=103005 | C11: Microsoft | D11: Official template pack | E11: Version 1.0, published 2024-07-15 | F11: 2026-09-30 | G11: Confirms the official table set: planning, current environment assessment, profiles, applications, compliance, and test and validation - mirrored and extended here | H11: No comments on the download centre | I11: Word format and two years old - predates the 2026 government feature changes and the deployments preview
A12: 8 | B12: Intune tenant documentation script - https://github.com/microsoft/intune-tenant-doc | C12: Microsoft | D12: Official script (archived) | E12: Repository archived 2026-09-22 | F12: 2026-09-30 | G12: Read-only tenant configuration capture listed on the Tooling tab | H12: Repository is archived and read-only, so no further issue discussion | I12: Archived - unmaintained; treat as a point-in-time tool
A13: 9 | B13: Automate Microsoft Intune as-built documentation - https://stealthpuppy.com/automate-intune-documentation-github/ | C13: Aaron Parker (stealthpuppy) | D13: Community / MVP blog | E13: Published 2022-03-02, updated 2026-09-28 | F13: 2026-09-30 | G13: IntuneCD-based automated as-built approach, and the argument for version-controlled capture over static documents | H13: No reader comments present on the page | I13: Recently updated - current
A14: 10 | B14: EPM Part 1: The end of local admin - https://msendpointmgr.com/2026/06/15/epm-part-1-the-end-of-local-admin-how-intune-endpoint-privilege-management-solves-a-problem-it-has-lived-with-for-decades/ | C14: MSEndpointMgr | D14: Community / MVP blog | E14: Published 2026-06-15 | F14: 2026-09-30 | G14: Audit-first method for local admin discovery: reporting-only elevation policy for 2-4 weeks, then persona mapping | H14: One comment (IT_Watcher, 2026-06-15) - supportive, no correction or dispute to the method | I14: Current
A15: 11 | B15: SCCM to Intune migration: identifying applications, packages and task sequences - https://www.systemcenterdudes.com/sccm-to-microsoft-intune-migration-identifying-applications-packages-and-task-sequences/ | C15: System Center Dudes | D15: Community / MVP blog | E15: Published 2025-01-28 | F15: 2026-09-30 | G15: SQL view and SSRS reporting method for the application inventory on the Applications tab | H15: Comment count zero - nothing to assess | I15: Method is stable but pre-2026; verify view names against your site version
A16: 12 | B16: Group Policy to Intune migration readiness guide - https://www.tiagoscarvalho.com/microsoft-intune/from-gpo-to-intune-migration-readiness-guide-2026 | C16: Tiago S. Carvalho | D16: Community blog | E16: Published 2026-05-21, updated 2026-05-26 | F16: 2026-09-30 | G16: GPO inventory register columns and the translation difficulty bands on the GPO mapping tab | H16: No comments section present on the page | I16: Author is described as a Microsoft 365 architect and technical writer - MVP status not verified; treated as a method source only, not an authority on facts
... A18: 14 | B18: Migration checklists (Configuration Manager) - https://learn.microsoft.com/intune/configmgr/core/migration/administrator-checklists-for-migration-planning | C18: Microsoft | D18: Official documentation | E18: ms.date 2016-12-29 | F18: 2026-09-30 | G18: Reviewed and deliberately NOT used | H18: No comments on Microsoft Learn | I18: Trap: the title suggests Intune migration, but it covers Configuration Manager hierarchy-to-hierarchy migration and dates from 2016

Sheet Dashboard
A1: Discovery progress
A2: Counts are formulas over the Discovery register. They populate when the workbook is opened in Excel.
A4: Domain | B4: Questions | C4: Open | D4: In progress | E4: Answered | F4: Blocked | G4: Must-do open
A5: Objectives and scope | B5: =COUNTIF('Discovery register'!$B$5:$B$173,$A5) | C5: =COUNTIFS('Discovery register'!$B$5:$B$173,$A5,'Discovery register'!$L$5:$L$173,"Open") | D5: =COUNTIFS('Discovery register'!$B$5:$B$173,$A5,'Discovery register'!$L$5:$L$173,"In progress") | E5: =COUNTIFS('Discovery register'!$B$5:$B$173,$A5,'Discovery register'!$L$5:$L$173,"Answered") | F5: =COUNTIFS('Discovery register'!$B$5:$B$173,$A5,'Discovery register'!$L$5:$L$173,"Blocked") | G5: =COUNTIFS('Discovery register'!$B$5:$B$173,$A5,'Discovery register'!$G$5:$G$173,"Must",'Discovery register'!$L$5:$L$173,"Open")
A6: Organisation | B6: =COUNTIF('Discovery register'!$B$5:$B$173,$A6) | C6: =COUNTIFS('Discovery register'!$B$5:$B$173,$A6,'Discovery register'!$L$5:$L$173,"Open") | D6: =COUNTIFS('Discovery register'!$B$5:$B$173,$A6,'Discovery register'!$L$5:$L$173,"In progress") | E6: =COUNTIFS('Discovery register'!$B$5:$B$173,$A6,'Discovery register'!$L$5:$L$173,"Answered") | F6: =COUNTIFS('Discovery register'!$B$5:$B$173,$A6,'Discovery register'!$L$5:$L$173,"Blocked") | G6: =COUNTIFS('Discovery register'!$B$5:$B$173,$A6,'Discovery register'!$G$5:$G$173,"Must",'Discovery register'!$L$5:$L$173,"Open")
A7: Device estate | B7: =COUNTIF('Discovery register'!$B$5:$B$173,$A7) | C7: =COUNTIFS('Discovery register'!$B$5:$B$173,$A7,'Discovery register'!$L$5:$L$173,"Open") | D7: =COUNTIFS('Discovery register'!$B$5:$B$173,$A7,'Discovery register'!$L$5:$L$173,"In progress") | E7: =COUNTIFS('Discovery register'!$B$5:$B$173,$A7,'Discovery register'!$L$5:$L$173,"Answered") | F7: =COUNTIFS('Discovery register'!$B$5:$B$173,$A7,'Discovery register'!$L$5:$L$173,"Blocked") | G7: =COUNTIFS('Discovery register'!$B$5:$B$173,$A7,'Discovery register'!$G$5:$G$173,"Must",'Discovery register'!$L$5:$L$173,"Open")
A8: Personas | B8: =COUNTIF('Discovery register'!$B$5:$B$173,$A8) | C8: =COUNTIFS('Discovery register'!$B$5:$B$173,$A8,'Discovery register'!$L$5:$L$173,"Open") | D8: =COUNTIFS('Discovery register'!$B$5:$B$173,$A8,'Discovery register'!$L$5:$L$173,"In progress") | E8: =COUNTIFS('Discovery register'!$B$5:$B$173,$A8,'Discovery register'!$L$5:$L$173,"Answered") | F8: =COUNTIFS('Discovery register'!$B$5:$B$173,$A8,'Discovery register'!$L$5:$L$173,"Blocked") | G8: =COUNTIFS('Discovery register'!$B$5:$B$173,$A8,'Discovery register'!$G$5:$G$173,"Must",'Discovery register'!$L$5:$L$173,"Open")
A9: Licensing and cost | B9: =COUNTIF('Discovery register'!$B$5:$B$173,$A9) | C9: =COUNTIFS('Discovery register'!$B$5:$B$173,$A9,'Discovery register'!$L$5:$L$173,"Open") | D9: =COUNTIFS('Discovery register'!$B$5:$B$173,$A9,'Discovery register'!$L$5:$L$173,"In progress") | E9: =COUNTIFS('Discovery register'!$B$5:$B$173,$A9,'Discovery register'!$L$5:$L$173,"Answered") | F9: =COUNTIFS('Discovery register'!$B$5:$B$173,$A9,'Discovery register'!$L$5:$L$173,"Blocked") | G9: =COUNTIFS('Discovery register'!$B$5:$B$173,$A9,'Discovery register'!$G$5:$G$173,"Must",'Discovery register'!$L$5:$L$173,"Open")
A10: Identity and access | B10: =COUNTIF('Discovery register'!$B$5:$B$173,$A10) | C10: =COUNTIFS('Discovery register'!$B$5:$B$173,$A10,'Discovery register'!$L$5:$L$173,"Open") | D10: =COUNTIFS('Discovery register'!$B$5:$B$173,$A10,'Discovery register'!$L$5:$L$173,"In progress") | E10: =COUNTIFS('Discovery register'!$B$5:$B$173,$A10,'Discovery register'!$L$5:$L$173,"Answered") | F10: =COUNTIFS('Discovery register'!$B$5:$B$173,$A10,'Discovery register'!$L$5:$L$173,"Blocked") | G10: =COUNTIFS('Discovery register'!$B$5:$B$173,$A10,'Discovery register'!$G$5:$G$173,"Must",'Discovery register'!$L$5:$L$173,"Open")
A11: Existing policy | B11: =COUNTIF('Discovery register'!$B$5:$B$173,$A11) | C11: =COUNTIFS('Discovery register'!$B$5:$B$173,$A11,'Discovery register'!$L$5:$L$173,"Open") | D11: =COUNTIFS('Discovery register'!$B$5:$B$173,$A11,'Discovery register'!$L$5:$L$173,"In progress") | E11: =COUNTIFS('Discovery register'!$B$5:$B$173,$A11,'Discovery register'!$L$5:$L$173,"Answered") | F11: =COUNTIFS('Discovery register'!$B$5:$B$173,$A11,'Discovery register'!$L$5:$L$173,"Blocked") | G11: =COUNTIFS('Discovery register'!$B$5:$B$173,$A11,'Discovery register'!$G$5:$G$173,"Must",'Discovery register'!$L$5:$L$173,"Open")
A12: Applications | B12: =COUNTIF('Discovery register'!$B$5:$B$173,$A12) | C12: =COUNTIFS('Discovery register'!$B$5:$B$173,$A12,'Discovery register'!$L$5:$L$173,"Open") | D12: =COUNTIFS('Discovery register'!$B$5:$B$173,$A12,'Discovery register'!$L$5:$L$173,"In progress") | E12: =COUNTIFS('Discovery register'!$B$5:$B$173,$A12,'Discovery register'!$L$5:$L$173,"Answered") | F12: =COUNTIFS('Discovery register'!$B$5:$B$173,$A12,'Discovery register'!$L$5:$L$173,"Blocked") | G12: =COUNTIFS('Discovery register'!$B$5:$B$173,$A12,'Discovery register'!$G$5:$G$173,"Must",'Discovery register'!$L$5:$L$173,"Open")
A13: Updates | B13: =COUNTIF('Discovery register'!$B$5:$B$173,$A13) | C13: =COUNTIFS('Discovery register'!$B$5:$B$173,$A13,'Discovery register'!$L$5:$L$173,"Open") | D13: =COUNTIFS('Discovery register'!$B$5:$B$173,$A13,'Discovery register'!$L$5:$L$173,"In progress") | E13: =COUNTIFS('Discovery register'!$B$5:$B$173,$A13,'Discovery register'!$L$5:$L$173,"Answered") | F13: =COUNTIFS('Discovery register'!$B$5:$B$173,$A13,'Discovery register'!$L$5:$L$173,"Blocked") | G13: =COUNTIFS('Discovery register'!$B$5:$B$173,$A13,'Discovery register'!$G$5:$G$173,"Must",'Discovery register'!$L$5:$L$173,"Open")
A14: Security | B14: =COUNTIF('Discovery register'!$B$5:$B$173,$A14) | C14: =COUNTIFS('Discovery register'!$B$5:$B$173,$A14,'Discovery register'!$L$5:$L$173,"Open") | D14: =COUNTIFS('Discovery register'!$B$5:$B$173,$A14,'Discovery register'!$L$5:$L$173,"In progress") | E14: =COUNTIFS('Discovery register'!$B$5:$B$173,$A14,'Discovery register'!$L$5:$L$173,"Answered") | F14: =COUNTIFS('Discovery register'!$B$5:$B$173,$A14,'Discovery register'!$L$5:$L$173,"Blocked") | G14: =COUNTIFS('Discovery register'!$B$5:$B$173,$A14,'Discovery register'!$G$5:$G$173,"Must",'Discovery register'!$L$5:$L$173,"Open")
A15: Network and PKI | B15: =COUNTIF('Discovery register'!$B$5:$B$173,$A15) | C15: =COUNTIFS('Discovery register'!$B$5:$B$173,$A15,'Discovery register'!$L$5:$L$173,"Open") | D15: =COUNTIFS('Discovery register'!$B$5:$B$173,$A15,'Discovery register'!$L$5:$L$173,"In progress") | E15: =COUNTIFS('Discovery register'!$B$5:$B$173,$A15,'Discovery register'!$L$5:$L$173,"Answered") | F15: =COUNTIFS('Discovery register'!$B$5:$B$173,$A15,'Discovery register'!$L$5:$L$173,"Blocked") | G15: =COUNTIFS('Discovery register'!$B$5:$B$173,$A15,'Discovery register'!$G$5:$G$173,"Must",'Discovery register'!$L$5:$L$173,"Open")
A16: Government | B16: =COUNTIF('Discovery register'!$B$5:$B$173,$A16) | C16: =COUNTIFS('Discovery register'!$B$5:$B$173,$A16,'Discovery register'!$L$5:$L$173,"Open") | D16: =COUNTIFS('Discovery register'!$B$5:$B$173,$A16,'Discovery register'!$L$5:$L$173,"In progress") | E16: =COUNTIFS('Discovery register'!$B$5:$B$173,$A16,'Discovery register'!$L$5:$L$173,"Answered") | F16: =COUNTIFS('Discovery register'!$B$5:$B$173,$A16,'Discovery register'!$L$5:$L$173,"Blocked") | G16: =COUNTIFS('Discovery register'!$B$5:$B$173,$A16,'Discovery register'!$G$5:$G$173,"Must",'Discovery register'!$L$5:$L$173,"Open")
... A21: Migration source | B21: =COUNTIF('Discovery register'!$B$5:$B$173,$A21) | C21: =COUNTIFS('Discovery register'!$B$5:$B$173,$A21,'Discovery register'!$L$5:$L$173,"Open") | D21: =COUNTIFS('Discovery register'!$B$5:$B$173,$A21,'Discovery register'!$L$5:$L$173,"In progress") | E21: =COUNTIFS('Discovery register'!$B$5:$B$173,$A21,'Discovery register'!$L$5:$L$173,"Answered") | F21: =COUNTIFS('Discovery register'!$B$5:$B$173,$A21,'Discovery register'!$L$5:$L$173,"Blocked") | G21: =COUNTIFS('Discovery register'!$B$5:$B$173,$A21,'Discovery register'!$G$5:$G$173,"Must",'Discovery register'!$L$5:$L$173,"Open")
A22: Total | B22: =SUM(B5:B21) | C22: =SUM(C5:C21) | D22: =SUM(D5:D21) | E22: =SUM(E5:E21) | F22: =SUM(F5:F21) | G22: =SUM(G5:G21)
A23: Government feature gaps flagged in the register | B23: =COUNTIF('Discovery register'!$I$5:$I$173,"GOV GAP*")
A24: Note | B24: Every flagged row must be confirmed against the Microsoft government service description before the design relies on it.
